abnf/__init__.py
abnf/parser.py
abnf/py.typed
abnf/typing.py
abnf/grammars/__init__.py
abnf/grammars/cors.py
abnf/grammars/misc.py
abnf/grammars/rfc2616.py
abnf/grammars/rfc3339.py
abnf/grammars/rfc3629.py
abnf/grammars/rfc3986.py
abnf/grammars/rfc3987.py
abnf/grammars/rfc4647.py
abnf/grammars/rfc5234.py
abnf/grammars/rfc5322.py
abnf/grammars/rfc5646.py
abnf/grammars/rfc5987.py
abnf/grammars/rfc6265.py
abnf/grammars/rfc6266.py
abnf/grammars/rfc7230.py
abnf/grammars/rfc7231.py
abnf/grammars/rfc7232.py
abnf/grammars/rfc7233.py
abnf/grammars/rfc7234.py
abnf/grammars/rfc7235.py
abnf/grammars/rfc7405.py
abnf/grammars/rfc7489.py
abnf/grammars/rfc8187.py
abnf/grammars/rfc9110.py
abnf/grammars/rfc9111.py
abnf/grammars/rfc9116.py
abnf-2.3.0.dist-info/LICENSE.txt
abnf-2.3.0.dist-info/METADATA
abnf-2.3.0.dist-info/WHEEL
abnf-2.3.0.dist-info/top_level.txt
abnf-2.3.0.dist-info/RECORD
