Metadata-Version: 2.1
Name: abnf
Version: 2.3.0
Summary: Parsers for ABNF grammars.
Home-page: https://github.com/declaresub/abnf
Author: Charles Yeomans
Author-email: charles@declaresub.com
License: MIT
Keywords: abnf,parser,generator
Platform: any
Classifier: Development Status :: 5 - Production/Stable
Classifier: Intended Audience :: Developers
Classifier: License :: OSI Approved :: MIT License
Classifier: Topic :: Software Development :: Code Generators
Classifier: Topic :: Software Development :: Interpreters
Classifier: Programming Language :: Python
Classifier: Programming Language :: Python :: 3
Classifier: Programming Language :: Python :: 3.8
Classifier: Programming Language :: Python :: 3.9
Classifier: Programming Language :: Python :: 3.10
Classifier: Programming Language :: Python :: 3.11
Classifier: Programming Language :: Python :: 3.12
Requires-Python: >=3.8
License-File: LICENSE.txt
